{
  "project_name": "WebPage Explainer",
  "alternatives": [
    {
      "name": "A11y Analyzer (Accessibility Assistant)",
      "path": "../a11y-analyzer-accessibility-assistant/",
      "similarity_reason": "Similar problem domain and category",
      "category": "design-tools"
    },
    {
      "name": "SVG Animation Exporter",
      "path": "../svg-animation-exporter/",
      "similarity_reason": "Similar problem domain and category",
      "category": "design-tools"
    },
    {
      "name": "Web Page to PDF Pro",
      "path": "../web-page-to-pdf-pro/",
      "similarity_reason": "Similar problem domain and category",
      "category": "design-tools"
    },
    {
      "name": "Accessibility Checker",
      "path": "../accessibility-checker/",
      "similarity_reason": "Similar problem domain and category",
      "category": "design-tools"
    },
    {
      "name": "Code Health Dashboard",
      "path": "../code-health-dashboard/",
      "similarity_reason": "Similar problem domain and category",
      "category": "design-tools"
    }
  ],
  "last_updated": "2024-01-01"
}